openwebvulndb/common/__init__.py
openwebvulndb/common/__main__.py
openwebvulndb/common/basemodel.py
openwebvulndb/common/config.py
openwebvulndb/common/cve.py
openwebvulndb/common/errors.py
openwebvulndb/common/hash.py
openwebvulndb/common/logs.py
openwebvulndb/common/manager.py
openwebvulndb/common/models.py
openwebvulndb/common/parallel.py
openwebvulndb/common/release.py
openwebvulndb/common/schemas.py
openwebvulndb/common/serialize.py
openwebvulndb/common/storage.py
openwebvulndb/common/vcs.py
openwebvulndb/common/version.py
openwebvulndb/common/versionbuilder.py
openwebvulndb/wordpress/__init__.py
openwebvulndb/wordpress/__main__.py
openwebvulndb/wordpress/errors.py
openwebvulndb/wordpress/parser.py
openwebvulndb/wordpress/repository.py
openwebvulndb/wordpress/vane.py
openwebvulndb_tools-1.1.1.dist-info/LICENSE.md
openwebvulndb_tools-1.1.1.dist-info/METADATA
openwebvulndb_tools-1.1.1.dist-info/WHEEL
openwebvulndb_tools-1.1.1.dist-info/top_level.txt
openwebvulndb_tools-1.1.1.dist-info/RECORD
